[
  {
    "ticker": "APTV",
    "company": "Aptiv PLC",
    "strategy": "Call Debit (Bullish)",
    "type": "bullish",
    "is_squeeze": false,
    "price": 60.37,
    "market_cap": 15145364480.0,
    "market_cap_str": "15.15B",
    "mcap": 15.14536448,
    "pe_check": true,
    "growth_check": false,
    "debt_check": true,
    "health": 85.209,
    "trailing_pe": 80.40667,
    "forward_pe": 6.532284,
    "earnings_growth": -0.485,
    "debt_to_equity": 85.209,
    "earnings_date": "2026-05-05",
    "weekly_available": false,
    "monthly_available": true,
    "is_new": false,
    "added_timestamp": "2026-04-06T16:30:51.762620",
    "reasoning": "Det: Price < BBL(61.66) | ADX: 33.2 | RSI 27.7 (Extreme: Buying Delta for sharp snap-back.)"
  },
  {
    "ticker": "BIIB",
    "company": "Biogen Inc.",
    "strategy": "Put Credit (Bullish)",
    "type": "bullish",
    "is_squeeze": false,
    "price": 174.68,
    "market_cap": 25632845824.0,
    "market_cap_str": "25.63B",
    "mcap": 25.632845824,
    "pe_check": true,
    "growth_check": false,
    "debt_check": true,
    "health": 36.466,
    "trailing_pe": 19.847727,
    "forward_pe": 10.944823,
    "earnings_growth": null,
    "debt_to_equity": 36.466,
    "earnings_date": "2026-04-30",
    "weekly_available": true,
    "monthly_available": true,
    "is_new": false,
    "added_timestamp": "2026-04-06T16:31:13.357235",
    "reasoning": "Det: Price < BBL(176.42) | ADX: 16.1 | RSI 38.2 (Moderate: Selling Theta.)"
  },
  {
    "ticker": "BK",
    "company": "The Bank of New York Mellon Cor",
    "strategy": "Call Credit (Bearish)",
    "type": "bearish",
    "is_squeeze": false,
    "price": 123.36,
    "market_cap": 86011035648.0,
    "market_cap_str": "86.01B",
    "mcap": 86.011035648,
    "pe_check": true,
    "growth_check": true,
    "debt_check": false,
    "health": null,
    "trailing_pe": 16.667566,
    "forward_pe": 13.136412,
    "earnings_growth": 0.265,
    "debt_to_equity": null,
    "earnings_date": "2026-04-16",
    "weekly_available": true,
    "monthly_available": true,
    "is_new": false,
    "added_timestamp": "2026-04-06T16:31:19.256707",
    "reasoning": "Det: Price > BBU(121.94) | ADX: 17.2 | RSI 65.1 (Moderate: Selling Theta.)"
  },
  {
    "ticker": "DAY",
    "company": "Dayforce, Inc.",
    "strategy": "Call Credit (Bearish)",
    "type": "bearish",
    "is_squeeze": false,
    "price": 69.86,
    "market_cap": 11180042240.0,
    "market_cap_str": "11.18B",
    "mcap": 11.18004224,
    "pe_check": false,
    "growth_check": false,
    "debt_check": true,
    "health": 45.53,
    "trailing_pe": null,
    "forward_pe": 25.551184,
    "earnings_growth": null,
    "debt_to_equity": 45.53,
    "earnings_date": "2026-02-11",
    "weekly_available": false,
    "monthly_available": false,
    "is_new": false,
    "added_timestamp": "2026-04-06T16:32:30.837233",
    "reasoning": "Det: Price > BBU(69.70) | ADX: 18.9 | RSI 63.9 (Moderate: Selling Theta.)"
  },
  {
    "ticker": "EBAY",
    "company": "eBay Inc.",
    "strategy": "Call Credit (Bearish)",
    "type": "bearish",
    "is_squeeze": false,
    "price": 97.66,
    "market_cap": 44151361536.0,
    "market_cap_str": "44.15B",
    "mcap": 44.151361536,
    "pe_check": true,
    "growth_check": false,
    "debt_check": false,
    "health": 155.623,
    "trailing_pe": 22.929577,
    "forward_pe": 14.646457,
    "earnings_growth": -0.222,
    "debt_to_equity": 155.623,
    "earnings_date": "2026-04-29",
    "weekly_available": true,
    "monthly_available": true,
    "is_new": false,
    "added_timestamp": "2026-04-06T16:32:54.972498",
    "reasoning": "Det: Price > BBU(95.70) | ADX: 15.0 | RSI 67.7 (Moderate: Selling Theta.)"
  },
  {
    "ticker": "ENPH",
    "company": "Enphase Energy, Inc.",
    "strategy": "Put Credit (Bullish)",
    "type": "bullish",
    "is_squeeze": false,
    "price": 33.57,
    "market_cap": 4411396096.0,
    "market_cap_str": "4.41B",
    "mcap": 4.411396096,
    "pe_check": true,
    "growth_check": false,
    "debt_check": false,
    "health": 114.421,
    "trailing_pe": 26.084806,
    "forward_pe": 12.513768,
    "earnings_growth": -0.377,
    "debt_to_equity": 114.421,
    "earnings_date": "2026-04-28",
    "weekly_available": true,
    "monthly_available": true,
    "is_new": false,
    "added_timestamp": "2026-04-06T16:33:02.826246",
    "reasoning": "Det: Price < BBL(34.05) | ADX: 17.0 | RSI 34.5 (Moderate: Selling Theta.)"
  },
  {
    "ticker": "EQIX",
    "company": "Equinix, Inc.",
    "strategy": "Put Debit (Bearish)",
    "type": "bearish",
    "is_squeeze": false,
    "price": 1012.5,
    "market_cap": 99853811712.0,
    "market_cap_str": "99.85B",
    "mcap": 99.853811712,
    "pe_check": true,
    "growth_check": false,
    "debt_check": false,
    "health": 160.291,
    "trailing_pe": 73.31462,
    "forward_pe": 58.736767,
    "earnings_growth": null,
    "debt_to_equity": 160.291,
    "earnings_date": "2026-04-29",
    "weekly_available": true,
    "monthly_available": true,
    "is_new": false,
    "added_timestamp": "2026-04-06T16:33:07.040392",
    "reasoning": "Det: Price > BBU(1003.89) | ADX: 26.5 | RSI 72.8 (Extreme: Buying Delta for sharp snap-back.)"
  },
  {
    "ticker": "FFIV",
    "company": "F5, Inc.",
    "strategy": "Call Credit (Bearish)",
    "type": "bearish",
    "is_squeeze": false,
    "price": 307.11,
    "market_cap": 17446117376.0,
    "market_cap_str": "17.45B",
    "mcap": 17.446117376,
    "pe_check": true,
    "growth_check": true,
    "debt_check": true,
    "health": 7.566,
    "trailing_pe": 25.44242,
    "forward_pe": 18.287405,
    "earnings_growth": 0.082,
    "debt_to_equity": 7.566,
    "earnings_date": "2026-04-27",
    "weekly_available": false,
    "monthly_available": true,
    "is_new": false,
    "added_timestamp": "2026-04-06T16:33:18.875995",
    "reasoning": "Det: Price > BBU(303.29) | ADX: 19.6 | RSI 63.6 (Moderate: Selling Theta.)"
  },
  {
    "ticker": "HOLX",
    "company": "Hologic, Inc.",
    "strategy": "Call Credit (Bearish)",
    "type": "bearish",
    "is_squeeze": false,
    "price": 76.01,
    "market_cap": 16969961472.0,
    "market_cap_str": "16.97B",
    "mcap": 16.969961472,
    "pe_check": true,
    "growth_check": false,
    "debt_check": true,
    "health": 48.051,
    "trailing_pe": 31.541492,
    "forward_pe": 15.665282,
    "earnings_growth": -0.109,
    "debt_to_equity": 48.051,
    "earnings_date": "2026-04-30",
    "weekly_available": true,
    "monthly_available": true,
    "is_new": false,
    "added_timestamp": "2026-04-06T16:34:00.966911",
    "reasoning": "Det: Price > BBU(75.94) | ADX: 18.8 | RSI 68.8 (Moderate: Selling Theta.)"
  },
  {
    "ticker": "INTC",
    "company": "Intel Corporation",
    "strategy": "Call Credit (Bearish)",
    "type": "bearish",
    "is_squeeze": false,
    "price": 50.36,
    "market_cap": 252581937152.0,
    "market_cap_str": "252.58B",
    "mcap": 252.581937152,
    "pe_check": false,
    "growth_check": false,
    "debt_check": true,
    "health": 37.282,
    "trailing_pe": null,
    "forward_pe": 50.70353,
    "earnings_growth": null,
    "debt_to_equity": 37.282,
    "earnings_date": "2026-04-23",
    "weekly_available": true,
    "monthly_available": true,
    "is_new": false,
    "added_timestamp": "2026-04-06T16:34:19.329667",
    "reasoning": "Det: Price > BBU(50.14) | ADX: 12.8 | RSI 60.4 (Moderate: Selling Theta.)"
  },
  {
    "ticker": "ICE",
    "company": "Intercontinental Exchange Inc.",
    "strategy": "Call Credit (Bearish)",
    "type": "bearish",
    "is_squeeze": false,
    "price": 166.38,
    "market_cap": 94469586944.0,
    "market_cap_str": "94.47B",
    "mcap": 94.469586944,
    "pe_check": true,
    "growth_check": true,
    "debt_check": true,
    "health": 70.077,
    "trailing_pe": 28.830156,
    "forward_pe": 19.400705,
    "earnings_growth": 0.219,
    "debt_to_equity": 70.077,
    "earnings_date": "2026-04-30",
    "weekly_available": true,
    "monthly_available": true,
    "is_new": false,
    "added_timestamp": "2026-04-06T16:34:20.013108",
    "reasoning": "Det: Price > BBU(165.06) | ADX: 22.2 | RSI 62.5 (Moderate: Selling Theta.)"
  },
  {
    "ticker": "SBAC",
    "company": "SBA Communications Corporation",
    "strategy": "Put Debit (Bearish)",
    "type": "bearish",
    "is_squeeze": false,
    "price": 213.12,
    "market_cap": 22504302592.0,
    "market_cap_str": "22.50B",
    "mcap": 22.504302592,
    "pe_check": false,
    "growth_check": true,
    "debt_check": false,
    "health": null,
    "trailing_pe": 21.734694,
    "forward_pe": 26.980469,
    "earnings_growth": 1.133,
    "debt_to_equity": null,
    "earnings_date": "2026-04-27",
    "weekly_available": true,
    "monthly_available": true,
    "is_new": false,
    "added_timestamp": "2026-04-06T16:36:56.775626",
    "reasoning": "Det: Price > BBU(207.22) | ADX: 30.3 | RSI 72.6 (Extreme: Buying Delta for sharp snap-back.)"
  },
  {
    "ticker": "STX",
    "company": "Seagate Technology Holdings PLC",
    "strategy": "Call Credit (Bearish)",
    "type": "bearish",
    "is_squeeze": false,
    "price": 454.74,
    "market_cap": 101994496000.0,
    "market_cap_str": "101.99B",
    "mcap": 101.994496,
    "pe_check": true,
    "growth_check": true,
    "debt_check": false,
    "health": 1046.623,
    "trailing_pe": 51.502377,
    "forward_pe": 22.841724,
    "earnings_growth": 0.765,
    "debt_to_equity": 1046.623,
    "earnings_date": "2026-05-05",
    "weekly_available": true,
    "monthly_available": true,
    "is_new": false,
    "added_timestamp": "2026-04-06T16:36:59.770088",
    "reasoning": "Det: Price > BBU(449.21) | ADX: 13.0 | RSI 61.9 (Moderate: Selling Theta.)"
  },
  {
    "ticker": "STT",
    "company": "State Street Corporation",
    "strategy": "Call Credit (Bearish)",
    "type": "bearish",
    "is_squeeze": false,
    "price": 129.99,
    "market_cap": 36307824640.0,
    "market_cap_str": "36.31B",
    "mcap": 36.30782464,
    "pe_check": true,
    "growth_check": false,
    "debt_check": false,
    "health": null,
    "trailing_pe": 13.828725,
    "forward_pe": 9.958432,
    "earnings_growth": -0.237,
    "debt_to_equity": null,
    "earnings_date": "2026-04-17",
    "weekly_available": true,
    "monthly_available": true,
    "is_new": false,
    "added_timestamp": "2026-04-06T16:37:12.145687",
    "reasoning": "Det: Price > BBU(129.55) | ADX: 16.8 | RSI 61.2 (Moderate: Selling Theta.)"
  },
  {
    "ticker": "TMUS",
    "company": "T-Mobile US, Inc.",
    "strategy": "Put Credit (Bullish)",
    "type": "bullish",
    "is_squeeze": false,
    "price": 198.99,
    "market_cap": 222549262336.0,
    "market_cap_str": "222.55B",
    "mcap": 222.549262336,
    "pe_check": true,
    "growth_check": false,
    "debt_check": false,
    "health": 208.851,
    "trailing_pe": 20.449127,
    "forward_pe": 14.155974,
    "earnings_growth": -0.295,
    "debt_to_equity": 208.851,
    "earnings_date": "2026-04-28",
    "weekly_available": true,
    "monthly_available": true,
    "is_new": false,
    "added_timestamp": "2026-04-06T16:37:20.399616",
    "reasoning": "Det: Price < BBL(200.47) | ADX: 20.1 | RSI 34.1 (Moderate: Selling Theta.)"
  },
  {
    "ticker": "VRSN",
    "company": "VeriSign, Inc.",
    "strategy": "Put Debit (Bearish)",
    "type": "bearish",
    "is_squeeze": false,
    "price": 271.48,
    "market_cap": 25169903616.0,
    "market_cap_str": "25.17B",
    "mcap": 25.169903616,
    "pe_check": true,
    "growth_check": true,
    "debt_check": false,
    "health": null,
    "trailing_pe": 30.81952,
    "forward_pe": 26.106838,
    "earnings_growth": 0.077,
    "debt_to_equity": null,
    "earnings_date": "2026-04-23",
    "weekly_available": true,
    "monthly_available": true,
    "is_new": false,
    "added_timestamp": "2026-04-06T16:37:54.239640",
    "reasoning": "Det: Price > BBU(262.49) | ADX: 30.8 | RSI 78.2 (Extreme: Buying Delta for sharp snap-back.)"
  },
  {
    "ticker": "MRVL",
    "company": "Marvell Technology, Inc.",
    "strategy": "Call Credit (Bearish)",
    "type": "bearish",
    "is_squeeze": false,
    "price": 108.96,
    "market_cap": 95206637568.0,
    "market_cap_str": "95.21B",
    "mcap": 95.206637568,
    "pe_check": true,
    "growth_check": true,
    "debt_check": true,
    "health": 33.479,
    "trailing_pe": 35.46417,
    "forward_pe": 20.17474,
    "earnings_growth": 0.979,
    "debt_to_equity": 33.479,
    "earnings_date": "2026-05-28",
    "weekly_available": true,
    "monthly_available": true,
    "is_new": false,
    "added_timestamp": "2026-04-06T16:38:51.457890",
    "reasoning": "Det: Price > BBU(107.36) | ADX: 17.0 | RSI 68.8 (Moderate: Selling Theta.)"
  },
  {
    "ticker": "AZN",
    "company": "AstraZeneca PLC",
    "strategy": "Call Credit (Bearish)",
    "type": "bearish",
    "is_squeeze": false,
    "price": 204.01,
    "market_cap": 316420620288.0,
    "market_cap_str": "316.42B",
    "mcap": 316.420620288,
    "pe_check": false,
    "growth_check": true,
    "debt_check": true,
    "health": 60.968,
    "trailing_pe": 31.256506,
    "forward_pe": 34.224674,
    "earnings_growth": 0.551,
    "debt_to_equity": 60.968,
    "earnings_date": "2026-04-29",
    "weekly_available": true,
    "monthly_available": true,
    "is_new": false,
    "added_timestamp": "2026-04-06T16:38:59.140623",
    "reasoning": "Det: Price > BBU(203.86) | ADX: 22.8 | RSI 64.7 (Moderate: Selling Theta.)"
  }
]